CHANGELOG.md
simd_structts/__init__.py
simd_structts/backends/__init__.py
simd_structts/backends/py_ssm/__init__.py
simd_structts/backends/py_ssm/filter.py
simd_structts/backends/py_ssm/model.py
simd_structts/backends/py_ssm/model_definition.py
simd_structts/backends/py_ssm/results.py
simd_structts/backends/py_ssm/smoother.py
simd_structts/backends/simd/__init__.py
simd_structts/backends/simd/kalman.py
simd_structts/backends/simd/model.py
simd_structts/backends/simd/results.py
simd_structts/backends/statsmodels/__init__.py
simd_structts/backends/statsmodels/model.py
simd_structts/backends/statsmodels/results.py
simd_structts/base/__init__.py
simd_structts/base/model.py
simd_structts/base/results.py
simd_structts/test_utils.py
simd_structts-0.2.1.dist-info/LICENSE
simd_structts-0.2.1.dist-info/WHEEL
simd_structts-0.2.1.dist-info/METADATA
simd_structts-0.2.1.dist-info/RECORD
