Metadata-Version: 2.1
Name: simd-structts
Version: 0.2.1
Summary: SIMD StuctTS Model with various backends
Home-page: https://github.com/vshulyak/simd-structts
License: MIT
Keywords: simd,kalman,time-series,forecasting
Author: Vladimir Shulyak
Author-email: vladimir@shulyak.net
Requires-Python: >=3.7,<4.0
Classifier: Development Status :: 4 - Beta
Classifier: License :: OSI Approved :: MIT License
Classifier: Operating System :: OS Independent
Classifier: Programming Language :: Python :: 3
Classifier: Programming Language :: Python :: 3.10
Classifier: Programming Language :: Python :: 3.7
Classifier: Programming Language :: Python :: 3.8
Classifier: Programming Language :: Python :: 3.9
Requires-Dist: simdkalman (>=1.0.1,<2.0.0)
Requires-Dist: statsmodels (>=0.13.0,<0.14.0)
Project-URL: Changelog, https://github.com/vshulyak/simd-structts/tree/main/CHANGELOG.rst
Project-URL: Documentation, https://github.com/vshulyak/simd-structts
Project-URL: Repository, https://github.com/vshulyak/simd-structts
